	{
	
     "createNewDataSource":{
	     "DataSourceName":"DSrcAutomation",
	     "FileExtenstion1":"csv",
	     "FileExtenstion2":"tsv",
	     "TransMetaData":"Order Line Item",
	     "FileSuffix":"_AutoSuffix",
	     "CalculationDate":"Ready for Activation Date",
	     "Product":"Base Product",
	     "ProgramAccount":"Bill To",
	     "Delimiter":"commas",
	     "ColumnName":"Name",
	     "ColumnOperator":"contains"    
	     
	     },
	     "duplicateDataSource":{
	     "DupDataSourceName":"DupAutomation",
	     "FileExtenstion1":"csv",
	     "FileExtenstion2":"tsv",
	     "TransMetaData":"Order Line Item",
	     "FileSuffix":"_DuplicateSuffix",
	     "CalculationDate":"Ready for Activation Date",
	     "Product":"Base Product",
	     "ProgramAccount":"Bill To",
	     "Delimiter":"commas"
	     },
	     "verifyValidationMsz":{
	     "DataSourceName":"ValidationAutomation",
	     "TransMetaData":"Order Line Item",
	     "CalculationDate":"Ready for Activation Date",
	     "Product":"Base Product",
	     "ProgramAccount":"Bill To",
	     "FileSuffix":"_AutoSuffix",
	     "FileExtenstion1":"csv",
	     "Delimiter":"commas"
	     
	     },
	     "verifyDelimiterSuffix":{
	     "DataSourceName":"Automation1",
	     "FileExtenstion1":"csv",
	     "FileExtenstion2":"tsv",
	     "TransMetaData":"Order Line Item",
	     "CalculationDate":"Ready for Activation Date",
	     "Product":"Base Product",
	     "ProgramAccount":"Bill To",
	     "Suffixscenario1":"_part",
	     "Suffixscenario2":"suffix1234",
	     "Suffixscenario3":"_#$%^&**suff676",
	     "Suffixscenario4":"tab_tab",
	     "Delimiterscenario1":"semicolon",
	     "Delimiterscenario2":"open braces",
	     "Delimiterscenario3":"forward slash",
	     "Delimiterscenario3":"tab"
	     },
	     "filterDataSource":{
	     "ColumnName":"Name",
	     "ColumnOperator":"contains",
	     "FilterValue":"Automation"
	     }
	     
}

		
	